{
	"tvos": "https://minh-ton.github.io/apple-updates/icons/tvos.png",
	"audioos": "https://minh-ton.github.io/apple-updates/icons/audioos.png",
	"pkg": "https://minh-ton.github.io/apple-updates/icons/pkg.png",

	"watchos8": "https://minh-ton.github.io/apple-updates/icons/watchos8.png",
	"watchos9": "https://minh-ton.github.io/apple-updates/icons/watchos9.png",

	"macos11": "https://minh-ton.github.io/apple-updates/icons/macos11.png",
	"macos12": "https://minh-ton.github.io/apple-updates/icons/macos12.png",
	"macos13": "https://minh-ton.github.io/apple-updates/icons/macos13.png",

	"ios14": "https://minh-ton.github.io/apple-updates/icons/ios14.png",
	"ios15": "https://minh-ton.github.io/apple-updates/icons/ios15.png",
	"ios16": "https://minh-ton.github.io/apple-updates/icons/ios16.png",

	"ipados14": "https://minh-ton.github.io/apple-updates/icons/ipados14.png",
	"ipados15": "https://minh-ton.github.io/apple-updates/icons/ipados15.png",
	"ipados16": "https://minh-ton.github.io/apple-updates/icons/ipados16.png"
}