{
    "ios": {
        "version": "16.0.2",
        "build": "20A380",
        "prodtype": "iPhone15,2",
        "model": "D73AP"
    },

    "ipados": {
        "version": "15.4",
        "build": "19E241",
        "prodtype": "iPad13,6",
        "model": "J518AP"
    },

    "watchos": {
        "version": "8.5",
        "build": "19T242",
        "prodtype": "Watch6,4",
        "model": "N158bAP"
    },

    "audioos": {
        "version": "15.4",
        "build": "19L440",
        "prodtype": "AudioAccessory5,1",
        "model": "B520AP"
    },
    
    "tvos": {
        "version": "15.4",
        "build": "19L440",
        "prodtype": "AppleTV11,1",
        "model": "J305AP"
    },

    "macos": {
        "version": "11.5",
        "build": "20G71",
        "prodtype": "MacBookPro17,1",
        "model": "J293AP"
    },

    "display": {
        "version": "15.4",
        "build": "19E241",
        "prodtype": "AppleDisplay2,1",
        "model": "J327AP"
    }
}